Workbook

Sheet Base Clientes
A1: age | B1: gender | C1: bmi | D1: children | E1: discount_eligibility | F1: region | G1: expenses | H1: premium
A2: 19 | B2: female | C2: 24.1 | D2: 0 | E2: yes | F2: south | G2: 1483.2083 | H2: 1744.951
A3: 18 | B3: male | C3: 23.5 | D3: 1 | E3: no | F3: southeast | G3: 2237.6079 | H3: 2632.4799
A4: 28 | B4: male | C4: 33 | D4: 3 | E4: no | F4: southeast | G4: 2046.0872 | H4: 2728.1162
A5: 33 | B5: male | C5: 23.3 | D5: 0 | E5: no | F5: midwest | G5: 2331.692 | H5: 2743.1671
A6: 32 | B6: male | C6: 23.4 | D6: 0 | E6: no | F6: midwest | G6: 1942.5013 | H6: 2285.2956
A7: 31 | B7: female | C7: 22.9 | D7: 0 | E7: no | F7: southeast | G7: 2375.7405 | H7: 2794.9889
A8: 46 | B8: female | C8: 33.4 | D8: 1 | E8: no | F8: southeast | G8: 4453.2339 | H8: 4241.1752
A9: 37 | B9: female | C9: 27.7 | D9: 3 | E9: no | F9: midwest | G9: 2326.6882 | H9: 3102.2509
A10: 37 | B10: male | C10: 29.8 | D10: 2 | E10: no | F10: northeast | G10: 1712.426 | H10: 2283.2346
A11: 60 | B11: female | C11: 25.8 | D11: 0 | E11: no | F11: midwest | G11: 4684.8206 | H11: 4461.7339
A12: 25 | B12: male | C12: 20.3 | D12: 0 | E12: no | F12: northeast | G12: 2168.5565 | H12: 2551.2429
A13: 62 | B13: female | C13: 26.3 | D13: 0 | E13: yes | F13: southeast | G13: 5417.6353 | H13: 5159.6527
... A1339: 61 | B1339: female | C1339: 29.1 | D1339: 0 | E1339: yes | F1339: midwest | G1339: 4541.902 | H1339: 4325.6209

Sheet Clusterização com Python
A1: Clusterização com K-Means
A3: 1 - Carregar a tabela do Excel pro Python
A4: 2 - Padronizar os dados
A6: 3 - Avaliar quantidade de clusters
A25: 4 - Rodando a Clusterização
A26: 5 - Acrescentando coluna 'Cluster' na base
A27: 6 - Exibindo base clusterizada

Sheet Base_Clusterizada
A1: age | B1: gender | C1: bmi | D1: children | E1: discount_eligibility | F1: region | G1: expenses | H1: premium | I1: discount_eligibility_tratado | J1: Cluster
A2: 19 | B2: female | C2: 24.1 | D2: 0 | E2: yes | F2: south | G2: 1483.2083 | H2: 1744.951 | I2: 1 | J2: 2
A3: 18 | B3: male | C3: 23.5 | D3: 1 | E3: no | F3: southeast | G3: 2237.6079 | H3: 2632.4799 | I3: 0 | J3: 0
A4: 28 | B4: male | C4: 33 | D4: 3 | E4: no | F4: southeast | G4: 2046.0872 | H4: 2728.1162 | I4: 0 | J4: 3
A5: 33 | B5: male | C5: 23.3 | D5: 0 | E5: no | F5: midwest | G5: 2331.692 | H5: 2743.1671 | I5: 0 | J5: 0
A6: 32 | B6: male | C6: 23.4 | D6: 0 | E6: no | F6: midwest | G6: 1942.5013 | H6: 2285.2956 | I6: 0 | J6: 0
A7: 31 | B7: female | C7: 22.9 | D7: 0 | E7: no | F7: southeast | G7: 2375.7405 | H7: 2794.9889 | I7: 0 | J7: 0
A8: 46 | B8: female | C8: 33.4 | D8: 1 | E8: no | F8: southeast | G8: 4453.2339 | H8: 4241.1752 | I8: 0 | J8: 1
A9: 37 | B9: female | C9: 27.7 | D9: 3 | E9: no | F9: midwest | G9: 2326.6882 | H9: 3102.2509 | I9: 0 | J9: 3
A10: 37 | B10: male | C10: 29.8 | D10: 2 | E10: no | F10: northeast | G10: 1712.426 | H10: 2283.2346 | I10: 0 | J10: 3
A11: 60 | B11: female | C11: 25.8 | D11: 0 | E11: no | F11: midwest | G11: 4684.8206 | H11: 4461.7339 | I11: 0 | J11: 1
A12: 25 | B12: male | C12: 20.3 | D12: 0 | E12: no | F12: northeast | G12: 2168.5565 | H12: 2551.2429 | I12: 0 | J12: 0
A13: 62 | B13: female | C13: 26.3 | D13: 0 | E13: yes | F13: southeast | G13: 5417.6353 | H13: 5159.6527 | I13: 1 | J13: 2
... A1339: 61 | B1339: female | C1339: 29.1 | D1339: 0 | E1339: yes | F1339: midwest | G1339: 4541.902 | H1339: 4325.6209 | I1339: 1 | J1339: 2

Sheet Quanto Cobrar
A1: Cluster | B1: age | C1: bmi | D1: children | E1: gender | F1: discount_eligibility | G1: region | H1: expenses | I1: premium | J1: Valor Premium Novo | K1: Lucro que teríamos | L1: Lucro que tivemos | N1: Cluster | O1: Margem Desejada
A2: 2 | B2: 19 | C2: 24.1 | D2: 0 | E2: female | F2: yes | G2: southwest | H2: 1483.2083 | I2: 1744.951 | J2: =VLOOKUP(A2,Planilha1!A:M,13,0) -> 3220.2324 | K2: =J2-H2 -> 1737.0241 | L2: =I2-H2 -> 261.74265 | N2: 0
A3: 0 | B3: 18 | C3: 23.5 | D3: 1 | E3: male | F3: no | G3: southeast | H3: 2237.6079 | I3: 2632.4799 | J3: =VLOOKUP(A3,Planilha1!A:M,13,0) -> 2511.822 | K3: =J3-H3 -> 274.21411 | L3: =I3-H3 -> 394.87199 | N3: 1
A4: 3 | B4: 28 | C4: 33 | D4: 3 | E4: male | F4: no | G4: southeast | H4: 2046.0872 | I4: 2728.1162 | J4: =VLOOKUP(A4,Planilha1!A:M,13,0) -> 3049.3551 | K4: =J4-H4 -> 1003.2679 | L4: =I4-H4 -> 682.02905 | N4: 2
A5: 0 | B5: 33 | C5: 23.3 | D5: 0 | E5: male | F5: no | G5: northwest | H5: 2331.692 | I5: 2743.1671 | J5: =VLOOKUP(A5,Planilha1!A:M,13,0) -> 2511.822 | K5: =J5-H5 -> 180.13 | L5: =I5-H5 -> 411.47507 | N5: 3
A6: 0 | B6: 32 | C6: 23.4 | D6: 0 | E6: male | F6: no | G6: northwest | H6: 1942.5013 | I6: 2285.2956 | J6: =VLOOKUP(A6,Planilha1!A:M,13,0) -> 2511.822 | K6: =J6-H6 -> 569.3208 | L6: =I6-H6 -> 342.79434
A7: 0 | B7: 31 | C7: 22.9 | D7: 0 | E7: female | F7: no | G7: southeast | H7: 2375.7405 | I7: 2794.9889 | J7: =VLOOKUP(A7,Planilha1!A:M,13,0) -> 2511.822 | K7: =J7-H7 -> 136.0815 | L7: =I7-H7 -> 419.24833 | N7: Lucro Antigo | O7: Lucro Novo
A8: 1 | B8: 46 | C8: 33.4 | D8: 1 | E8: female | F8: no | G8: southeast | H8: 4453.2339 | I8: 4241.1752 | J8: =VLOOKUP(A8,Planilha1!A:M,13,0) -> 6326.3485 | K8: =J8-H8 -> 1873.1146 | L8: =I8-H8 -> -212.05876 | N8: =SUM(L:L) -> 338558.75 | O8: =SUM(K:K) -> 1268727.3
A9: 3 | B9: 37 | C9: 27.7 | D9: 3 | E9: female | F9: no | G9: northwest | H9: 2326.6882 | I9: 3102.2509 | J9: =VLOOKUP(A9,Planilha1!A:M,13,0) -> 3049.3551 | K9: =J9-H9 -> 722.66691 | L9: =I9-H9 -> 775.56272
A10: 3 | B10: 37 | C10: 29.8 | D10: 2 | E10: male | F10: no | G10: northeast | H10: 1712.426 | I10: 2283.2346 | J10: =VLOOKUP(A10,Planilha1!A:M,13,0) -> 3049.3551 | K10: =J10-H10 -> 1336.9291 | L10: =I10-H10 -> 570.80866
A11: 1 | B11: 60 | C11: 25.8 | D11: 0 | E11: female | F11: no | G11: northwest | H11: 4684.8206 | I11: 4461.7339 | J11: =VLOOKUP(A11,Planilha1!A:M,13,0) -> 6326.3485 | K11: =J11-H11 -> 1641.5279 | L11: =I11-H11 -> -223.08669
A12: 0 | B12: 25 | C12: 20.3 | D12: 0 | E12: male | F12: no | G12: northeast | H12: 2168.5565 | I12: 2551.2429 | J12: =VLOOKUP(A12,Planilha1!A:M,13,0) -> 2511.822 | K12: =J12-H12 -> 343.26556 | L12: =I12-H12 -> 382.68644
A13: 2 | B13: 62 | C13: 26.3 | D13: 0 | E13: female | F13: yes | G13: southeast | H13: 5417.6353 | I13: 5159.6527 | J13: =VLOOKUP(A13,Planilha1!A:M,13,0) -> 3220.2324 | K13: =J13-H13 -> -2197.4029 | L13: =I13-H13 -> -257.98263
A14: 0 | B14: 23 | C14: 21.2 | D14: 0 | E14: male | F14: no | G14: southwest | H14: 1802.1615 | I14: 2120.19 | J14: =VLOOKUP(A14,Planilha1!A:M,13,0) -> 2511.822 | K14: =J14-H14 -> 709.66055 | L14: =I14-H14 -> 318.0285
A15: 1 | B15: 56 | C15: 39.8 | D15: 0 | E15: female | F15: no | G15: southeast | H15: 3641.0645 | I15: 3467.6805 | J15: =VLOOKUP(A15,Planilha1!A:M,13,0) -> 6326.3485 | K15: =J15-H15 -> 2685.284 | L15: =I15-H15 -> -173.38403
A16: 2 | B16: 27 | C16: 24.2 | D16: 0 | E16: male | F16: yes | G16: southeast | H16: 1460.3167 | I16: 1718.0197 | J16: =VLOOKUP(A16,Planilha1!A:M,13,0) -> 3220.2324 | K16: =J16-H16 -> 1759.9157 | L16: =I16-H16 -> 257.70295
A17: 0 | B17: 19 | C17: 25.8 | D17: 1 | E17: male | F17: no | G17: southwest | H17: 1680.3079 | I17: 1976.8328 | J17: =VLOOKUP(A17,Planilha1!A:M,13,0) -> 2511.822 | K17: =J17-H17 -> 831.51413 | L17: =I17-H17 -> 296.52493
A18: 1 | B18: 52 | C18: 30.8 | D18: 1 | E18: female | F18: no | G18: northeast | H18: 3924.9202 | I18: 3738.0192 | J18: =VLOOKUP(A18,Planilha1!A:M,13,0) -> 6326.3485 | K18: =J18-H18 -> 2401.4284 | L18: =I18-H18 -> -186.90096
A19: 0 | B19: 23 | C19: 25.8 | D19: 0 | E19: male | F19: no | G19: northeast | H19: 1787.5455 | I19: 2102.9947 | J19: =VLOOKUP(A19,Planilha1!A:M,13,0) -> 2511.822 | K19: =J19-H19 -> 724.27657 | L19: =I19-H19 -> 315.4492
A20: 1 | B20: 56 | C20: 40.3 | D20: 0 | E20: male | F20: no | G20: southwest | H20: 4404.9074 | I20: 4195.1499 | J20: =VLOOKUP(A20,Planilha1!A:M,13,0) -> 6326.3485 | K20: =J20-H20 -> 1921.4412 | L20: =I20-H20 -> -209.75749
... A1339: 2 | B1339: 61 | C1339: 29.1 | D1339: 0 | E1339: female | F1339: yes | G1339: northwest | H1339: 4541.902 | I1339: 4325.6209 | J1339: =VLOOKUP(A1339,Planilha1!A:M,13,0) -> 3220.2324 | K1339: =J1339-H1339 -> -1321.6696 | L1339: =I1339-H1339 -> -216.28105

Sheet Planilha1
A3: Rótulos de Linha | B3: Média de age | C3: Média de bmi | D3: Média de children | E3: Média de discount_eligibility_tratado | F3: Média de expenses | G3: DesvPad de expenses | H3: Média de premium | I3: Coeficiente Variação (expenses) | J3: Lucro médio | K3: Margem | L3: Margem desejada | M3: Preço Alvo
A4: 0 | B4: 26.220339 | C4: 22.830993 | D4: 0.52784504 | E4: 0 | F4: 1883.8665 | G4: 328.1805 | H4: 2216.3136 | I4: =G4/F4 -> 0.17420581 | J4: =H4-F4 -> 332.44704 | K4: =J4/H4 -> 0.15 | L4: 0.25 | M4: =F4/(1-L4) -> 2511.822
A5: 1 | B5: 52.820225 | C5: 31.826124 | D5: 0.40168539 | E5: 0 | F5: 4744.7614 | G5: 705.15912 | H5: 4523.1808 | I5: =G5/F5 -> 0.14861846 | J5: =H5-F5 -> -221.5806 | K5: =J5/H5 -> -0.048987784 | L5: 0.25 | M5: =F5/(1-L5) -> 6326.3485
A6: 2 | B6: 38.514599 | C6: 28.054745 | D6: 1.1131387 | E6: 1 | F6: 2576.1859 | G6: 1375.2247 | H6: 2832.5492 | I6: =G6/F6 -> 0.53382198 | J6: =H6-F6 -> 256.36331 | K6: =J6/H6 -> 0.090506216 | L6: 0.2 | M6: =F6/(1-L6) -> 3220.2324
A7: 3 | B7: 41.60339 | C7: 31.691186 | D7: 2.7084746 | E7: 0 | F7: 2134.5486 | G7: 681.92985 | H7: 2846.0647 | I7: =G7/F7 -> 0.31947264 | J7: =H7-F7 -> 711.51619 | K7: =J7/H7 -> 0.25 | L7: 0.3 | M7: =F7/(1-L7) -> 3049.3551
A8: Total Geral | B8: 39.207025 | C8: 28.247534 | D8: 1.0949178 | E8: 0.20478326 | F8: 2842.1067 | G8: 1423.4306 | H8: 3095.1401
A11: Cluster 0 | B11: Mais jovem, imc, baixo, poucos filhos
A12: Cluster 1 | B12: Mais velho, imc mais alto, poucos filhos
A13: Cluster 2 | B13: Clientes com desconto
A14: Cluster 3 | B14: Meia idade, imc mais alto, muitos filhos
